[
    {
        "entity_type": "Artifact",
        "created_at": "2024-08-13T06:11:05.842Z",
        "updated_at": "2024-08-13T06:11:28.958Z",
        "objectMarking": [
            {
                "id": "5099de8b-f185-46c7-a4cc-32585f0d3363",
                "standard_id": "marking-definition--613f2e26-407d-48c7-9eca-b8e91df99dc9",
                "entity_type": "Marking-Definition",
                "definition_type": "TLP",
                "definition": "TLP:CLEAR",
                "created": "2024-05-02T14:47:14.079Z",
                "modified": "2024-05-02T14:53:28.555Z",
                "x_opencti_order": 1,
                "x_opencti_color": "#ffffff",
                "createdById": null
            }
        ],
        "objectLabel": [
            {
                "id": "9e3508f9-aa82-463e-8cb5-27b73fddf0ef",
                "value": "malware-bazaar",
                "color": "#54483b",
                "createdById": null
            },
            {
                "id": "fe90db1a-ca63-4112-8d79-9c90a8247395",
                "value": "mimicsecretservice",
                "color": "#54483b",
                "createdById": null
            },
            {
                "id": "2f9752f5-2aab-4a4d-a084-964519a94c24",
                "value": "msi",
                "color": "#83a701",
                "createdById": null
            }
        ],
        "observable_value": "d41110ef6ac26194061967efc74514440b566e23941c1eda0184b2c89e8e38a7c11878cc9c060646ba4db5c3267ed97355d36dc20d6c4eed97a1b0c8c64e7abe",
        "x_opencti_description": "Uploaded to MalwareBazaar by Twitter user: JAMESWT_MHT.",
        "x_opencti_score": null,
        "payload_bin": null,
        "url": null,
        "encryption_algorithm": null,
        "decryption_key": null,
        "hashes": [
            {
                "algorithm": "MD5",
                "hash": "5b1323cfcddc4fd7de98c94ce9ce8b66"
            },
            {
                "algorithm": "SHA-1",
                "hash": "0286343f9d0139c744d871f7778661d87535f4fe"
            },
            {
                "algorithm": "SHA-256",
                "hash": "a7297883de84d73fb4965c00228144a0e53c573ad3b7291be39bc6d9c284454c"
            },
            {
                "algorithm": "SHA-512",
                "hash": "d41110ef6ac26194061967efc74514440b566e23941c1eda0184b2c89e8e38a7c11878cc9c060646ba4db5c3267ed97355d36dc20d6c4eed97a1b0c8c64e7abe"
            }
        ]
    }
]